{
    "startDate": "2018-01-01",
    "endDate": "2018-09-30",
    "year": "2018",
    "quarter": "Q3",
    "symbol": "WERN",
    "data": {
        "bs": [
            {
                "label": "Cash and cash equivalents",
                "concept": "CashAndCashEquivalentsAtCarryingValue",
                "unit": "usd",
                "value": 9650000
            },
            {
                "label": "Accounts receivable, trade, less allowance of $8,750 and $8,250, respectively",
                "concept": "AccountsReceivableNetCurrent",
                "unit": "usd",
                "value": 324911000
            },
            {
                "label": "Other receivables",
                "concept": "OtherReceivables",
                "unit": "usd",
                "value": 27559000
            },
            {
                "label": "Inventories and supplies",
                "concept": "InventoryNet",
                "unit": "usd",
                "value": 11805000
            },
            {
                "label": "Prepaid taxes, licenses and permits",
                "concept": "wern:PrepaidTaxesLicensesAndPermits",
                "unit": "usd",
                "value": 7327000
            },
            {
                "label": "Other current assets",
                "concept": "OtherAssetsCurrent",
                "unit": "usd",
                "value": 38595000
            },
            {
                "label": "Current assets:",
                "concept": "AssetsCurrent",
                "unit": "usd",
                "value": 419847000
            },
            {
                "label": "Property and equipment",
                "concept": "PropertyPlantAndEquipmentGross",
                "unit": "usd",
                "value": 2249911000
            },
            {
                "label": "Less \u2013 accumulated depreciation",
                "concept": "AccumulatedDepreciationDepletionAndAmortizationPropertyPlantAndEquipment",
                "unit": "usd",
                "value": 781262000
            },
            {
                "label": "Property and equipment, net",
                "concept": "PropertyPlantAndEquipmentNet",
                "unit": "usd",
                "value": 1468649000
            },
            {
                "label": "Other non-current assets",
                "concept": "OtherAssetsNoncurrent",
                "unit": "usd",
                "value": 144640000
            },
            {
                "label": "ASSETS",
                "concept": "Assets",
                "unit": "usd",
                "value": 2033136000
            },
            {
                "label": "Checks issued in excess of cash balances",
                "concept": "BankOverdrafts",
                "unit": "usd",
                "value": 3299000
            },
            {
                "label": "Accounts payable",
                "concept": "AccountsPayableCurrent",
                "unit": "usd",
                "value": 90013000
            },
            {
                "label": "Current portion of long-term debt",
                "concept": "LinesOfCreditCurrent",
                "unit": "usd",
                "value": 75000000
            },
            {
                "label": "Insurance and claims accruals",
                "concept": "SelfInsuranceReserveCurrent",
                "unit": "usd",
                "value": 65021000
            },
            {
                "label": "Accrued payroll",
                "concept": "EmployeeRelatedLiabilitiesCurrent",
                "unit": "usd",
                "value": 37787000
            },
            {
                "label": "Other current liabilities",
                "concept": "OtherLiabilitiesCurrent",
                "unit": "usd",
                "value": 26757000
            },
            {
                "label": "Current liabilities:",
                "concept": "LiabilitiesCurrent",
                "unit": "usd",
                "value": 297877000
            },
            {
                "label": "Long-term debt, net of current portion",
                "concept": "LongTermLineOfCredit",
                "unit": "usd",
                "value": 50000000
            },
            {
                "label": "Other long-term liabilities",
                "concept": "OtherLiabilitiesNoncurrent",
                "unit": "usd",
                "value": 11646000
            },
            {
                "label": "Insurance and claims accruals, net of current portion",
                "concept": "SelfInsuranceReserveNoncurrent",
                "unit": "usd",
                "value": 208560000
            },
            {
                "label": "Deferred income taxes",
                "concept": "DeferredTaxLiabilitiesNoncurrent",
                "unit": "usd",
                "value": 221552000
            },
            {
                "label": "Commitments and contingencies",
                "concept": "CommitmentsAndContingencies",
                "unit": "usd",
                "value": "N/A"
            },
            {
                "label": "Common stock, $0.01 par value, 200,000,000 shares authorized; 80,533,536 shares issued; 71,194,303 and 72,409,222 shares outstanding, respectively",
                "concept": "CommonStockValue",
                "unit": "usd",
                "value": 805000
            },
            {
                "label": "Paid-in capital",
                "concept": "AdditionalPaidInCapitalCommonStock",
                "unit": "usd",
                "value": 106904000
            },
            {
                "label": "Retained earnings",
                "concept": "RetainedEarningsAccumulatedDeficit",
                "unit": "usd",
                "value": 1365523000
            },
            {
                "label": "Accumulated other comprehensive loss",
                "concept": "AccumulatedOtherComprehensiveIncomeLossNetOfTax",
                "unit": "usd",
                "value": -13659000
            },
            {
                "label": "Treasury stock, at cost; 9,339,233 and 8,124,314 shares, respectively",
                "concept": "TreasuryStockValue",
                "unit": "usd",
                "value": 216072000
            },
            {
                "label": "Stockholders\u2019 equity:",
                "concept": "StockholdersEquity",
                "unit": "usd",
                "value": 1243501000
            },
            {
                "label": "LIABILITIES AND STOCKHOLDERS\u2019 EQUITY",
                "concept": "LiabilitiesAndStockholdersEquity",
                "unit": "usd",
                "value": 2033136000
            }
        ],
        "cf": [
            {
                "label": "Net income",
                "concept": "NetIncomeLoss",
                "unit": "usd",
                "value": 113585000
            },
            {
                "label": "Depreciation",
                "concept": "Depreciation",
                "unit": "usd",
                "value": 170439000
            },
            {
                "label": "Deferred income taxes",
                "concept": "DeferredIncomeTaxExpenseBenefit",
                "unit": "usd",
                "value": 25114000
            },
            {
                "label": "Gain on disposal of property and equipment",
                "concept": "GainLossOnSaleOfPropertyPlantEquipment",
                "unit": "usd",
                "value": 15922000
            },
            {
                "label": "Award Type [Domain]",
                "concept": "ShareBasedCompensation",
                "unit": "usd",
                "value": 5507000
            },
            {
                "label": "Insurance and claims accruals, net of current portion",
                "concept": "wern:IncreaseDecreaseInSelfInsuranceReservesNoncurrent",
                "unit": "usd",
                "value": -21100000
            },
            {
                "label": "Other",
                "concept": "OtherOperatingActivitiesCashFlowStatement",
                "unit": "usd",
                "value": -5081000
            },
            {
                "label": "Accounts receivable, net",
                "concept": "IncreaseDecreaseInAccountsReceivable",
                "unit": "usd",
                "value": 20737000
            },
            {
                "label": "Other current assets",
                "concept": "IncreaseDecreaseInOtherCurrentAssets",
                "unit": "usd",
                "value": 9535000
            },
            {
                "label": "Accounts payable",
                "concept": "IncreaseDecreaseInAccountsPayableTrade",
                "unit": "usd",
                "value": 11742000
            },
            {
                "label": "Other current liabilities",
                "concept": "IncreaseDecreaseInOtherCurrentLiabilities",
                "unit": "usd",
                "value": 6301000
            },
            {
                "label": "Cash flows from operating activities:",
                "concept": "NetCashProvidedByUsedInOperatingActivities",
                "unit": "usd",
                "value": 302513000
            },
            {
                "label": "Additions to property and equipment",
                "concept": "PaymentsToAcquirePropertyPlantAndEquipment",
                "unit": "usd",
                "value": 412557000
            },
            {
                "label": "Proceeds from sales of property and equipment",
                "concept": "ProceedsFromSaleOfPropertyPlantAndEquipment",
                "unit": "usd",
                "value": 123267000
            },
            {
                "label": "Issuance of notes receivable",
                "concept": "PaymentsToAcquireNotesReceivable",
                "unit": "usd",
                "value": 3300000
            },
            {
                "label": "Decrease in notes receivable",
                "concept": "ProceedsFromCollectionOfNotesReceivable",
                "unit": "usd",
                "value": 15846000
            },
            {
                "label": "Cash flows from investing activities:",
                "concept": "NetCashProvidedByUsedInInvestingActivities",
                "unit": "usd",
                "value": -276744000
            },
            {
                "label": "Repayments of short-term debt",
                "concept": "RepaymentsOfLinesOfCredit",
                "unit": "usd",
                "value": 40000000
            },
            {
                "label": "Proceeds from issuance of short-term debt",
                "concept": "ProceedsFromLinesOfCredit",
                "unit": "usd",
                "value": 40000000
            },
            {
                "label": "Repayments of long-term debt",
                "concept": "RepaymentsOfLongTermLinesOfCredit",
                "unit": "usd",
                "value": 20000000
            },
            {
                "label": "Proceeds from issuance of long-term debt",
                "concept": "ProceedsFromLongTermLinesOfCredit",
                "unit": "usd",
                "value": 70000000
            },
            {
                "label": "Change in net checks issued in excess of cash balances",
                "concept": "IncreaseDecreaseInBookOverdrafts",
                "unit": "usd",
                "value": -18240000
            },
            {
                "label": "Dividends on common stock",
                "concept": "PaymentsOfDividendsCommonStock",
                "unit": "usd",
                "value": 16605000
            },
            {
                "label": "Repurchases of common stock",
                "concept": "PaymentsForRepurchaseOfCommonStock",
                "unit": "usd",
                "value": 46413000
            },
            {
                "label": "Tax withholding related to net share settlements of restricted stock awards",
                "concept": "PaymentsRelatedToTaxWithholdingForShareBasedCompensation",
                "unit": "usd",
                "value": 679000
            },
            {
                "label": "Stock options exercised",
                "concept": "ProceedsFromStockOptionsExercised",
                "unit": "usd",
                "value": 476000
            },
            {
                "label": "Cash flows from financing activities:",
                "concept": "NetCashProvidedByUsedInFinancingActivities",
                "unit": "usd",
                "value": -31461000
            },
            {
                "label": "Effect of exchange rate fluctuations on cash",
                "concept": "EffectOfExchangeRateOnCashAndCashEquivalents",
                "unit": "usd",
                "value": 211000
            },
            {
                "label": "Net increase (decrease) in cash, cash equivalents and restricted cash",
                "concept": "CashCashEquivalentsRestrictedCashAndRestrictedCashEquivalentsPeriodIncreaseDecreaseIncludingExchangeRateEffect",
                "unit": "usd",
                "value": -5481000
            },
            {
                "label": "Interest paid",
                "concept": "InterestPaid",
                "unit": "usd",
                "value": 1699000
            },
            {
                "label": "Income taxes paid",
                "concept": "IncomeTaxesPaidNet",
                "unit": "usd",
                "value": 6332000
            },
            {
                "label": "Notes receivable issued upon sale of property and equipment",
                "concept": "NotesIssued1",
                "unit": "usd",
                "value": 8054000
            },
            {
                "label": "Change in fair value of interest rate swap",
                "concept": "IncreaseDecreaseInFairValueOfInterestRateFairValueHedgingInstruments1",
                "unit": "usd",
                "value": 377000
            },
            {
                "label": "Property and equipment acquired included in accounts payable",
                "concept": "CapitalExpendituresIncurredButNotYetPaid",
                "unit": "usd",
                "value": 4797000
            },
            {
                "label": "Property and equipment disposed included in other receivables",
                "concept": "wern:PropertyAndEquipmentDisposedIncludedInOtherReceivables",
                "unit": "usd",
                "value": 1007000
            }
        ],
        "ic": [
            {
                "label": "Net income",
                "concept": "NetIncomeLoss",
                "unit": "usd",
                "value": 113585000
            },
            {
                "label": "Foreign currency translation adjustments",
                "concept": "OtherComprehensiveIncomeLossForeignCurrencyTransactionAndTranslationAdjustmentNetOfTax",
                "unit": "usd",
                "value": 1799000
            },
            {
                "label": "Change in fair value of interest rate swap",
                "concept": "OtherComprehensiveIncomeUnrealizedGainLossOnDerivativesArisingDuringPeriodNetOfTax",
                "unit": "usd",
                "value": 377000
            },
            {
                "label": "Other comprehensive income (loss):",
                "concept": "OtherComprehensiveIncomeLossNetOfTax",
                "unit": "usd",
                "value": 2176000
            },
            {
                "label": "Comprehensive income",
                "concept": "ComprehensiveIncomeNetOfTax",
                "unit": "usd",
                "value": 115761000
            },
            {
                "label": "Operating revenues",
                "concept": "Revenues",
                "unit": "usd",
                "value": 1811549000
            },
            {
                "label": "Salaries, wages and benefits",
                "concept": "LaborAndRelatedExpense",
                "unit": "usd",
                "value": 580515000
            },
            {
                "label": "Fuel",
                "concept": "FuelCosts",
                "unit": "usd",
                "value": 191769000
            },
            {
                "label": "Supplies and maintenance",
                "concept": "DirectOperatingMaintenanceSuppliesCosts",
                "unit": "usd",
                "value": 138556000
            },
            {
                "label": "Taxes and licenses",
                "concept": "DirectTaxesAndLicensesCosts",
                "unit": "usd",
                "value": 63607000
            },
            {
                "label": "Insurance and claims",
                "concept": "OperatingInsuranceAndClaimsCostsProduction",
                "unit": "usd",
                "value": 73858000
            },
            {
                "label": "Depreciation",
                "concept": "Depreciation",
                "unit": "usd",
                "value": 170439000
            },
            {
                "label": "Rent and purchased transportation",
                "concept": "wern:RentAndPurchasedTransportation",
                "unit": "usd",
                "value": 435225000
            },
            {
                "label": "Communications and utilities",
                "concept": "DirectCommunicationsAndUtilitiesCosts",
                "unit": "usd",
                "value": 12028000
            },
            {
                "label": "Other",
                "concept": "OtherCostAndExpenseOperating",
                "unit": "usd",
                "value": -3732000
            },
            {
                "label": "Operating expenses:",
                "concept": "CostsAndExpenses",
                "unit": "usd",
                "value": 1662265000
            },
            {
                "label": "Operating income",
                "concept": "OperatingIncomeLoss",
                "unit": "usd",
                "value": 149284000
            },
            {
                "label": "Interest expense",
                "concept": "InterestExpense",
                "unit": "usd",
                "value": 1842000
            },
            {
                "label": "Interest income",
                "concept": "InvestmentIncomeInterest",
                "unit": "usd",
                "value": 2079000
            },
            {
                "label": "Other",
                "concept": "OtherNonoperatingIncomeExpense",
                "unit": "usd",
                "value": -172000
            },
            {
                "label": "Other expense (income):",
                "concept": "NonoperatingIncomeExpense",
                "unit": "usd",
                "value": 65000
            },
            {
                "label": "Income before income taxes",
                "concept": "IncomeLossFromContinuingOperationsBeforeIncomeTaxesMinorityInterestAndIncomeLossFromEquityMethodInvestments",
                "unit": "usd",
                "value": 149349000
            },
            {
                "label": "Income taxes",
                "concept": "IncomeTaxExpenseBenefit",
                "unit": "usd",
                "value": 35764000
            },
            {
                "label": "Basic",
                "concept": "EarningsPerShareBasic",
                "unit": "usd/shares",
                "value": 1.58
            },
            {
                "label": "Diluted",
                "concept": "EarningsPerShareDiluted",
                "unit": "usd/shares",
                "value": 1.57
            },
            {
                "label": "Dividends declared per share",
                "concept": "CommonStockDividendsPerShareDeclared",
                "unit": "usd/shares",
                "value": 0.25
            },
            {
                "label": "Basic",
                "concept": "WeightedAverageNumberOfSharesOutstandingBasic",
                "unit": "shares",
                "value": 72001000
            },
            {
                "label": "Diluted",
                "concept": "WeightedAverageNumberOfDilutedSharesOutstanding",
                "unit": "shares",
                "value": 72300000
            }
        ]
    }
}