{
    "startDate": "2020-03-01",
    "endDate": "2020-05-31",
    "year": "2021",
    "quarter": "Q1",
    "symbol": "ANVI",
    "data": {
        "bs": [
            {
                "label": "",
                "concept": "Cash",
                "unit": "usd",
                "value": 1161
            },
            {
                "label": "",
                "concept": "PrepaidExpenseCurrent",
                "unit": "usd",
                "value": 7000
            },
            {
                "label": "",
                "concept": "AssetsCurrent",
                "unit": "usd",
                "value": 8161
            },
            {
                "label": "",
                "concept": "Assets",
                "unit": "usd",
                "value": 8161
            },
            {
                "label": "",
                "concept": "AccountsPayableCurrent",
                "unit": "usd",
                "value": 37497
            },
            {
                "label": "",
                "concept": "AccruedLiabilitiesCurrent",
                "unit": "usd",
                "value": 864000
            },
            {
                "label": "",
                "concept": "DueToOfficersOrStockholdersCurrent",
                "unit": "usd",
                "value": 239442
            },
            {
                "label": "",
                "concept": "LiabilitiesCurrent",
                "unit": "usd",
                "value": 1140939
            },
            {
                "label": "",
                "concept": "Liabilities",
                "unit": "usd",
                "value": 1140939
            },
            {
                "label": "",
                "concept": "PreferredStockValue",
                "unit": "usd",
                "value": "N/A"
            },
            {
                "label": "",
                "concept": "CommonStockValue",
                "unit": "usd",
                "value": 119950
            },
            {
                "label": "",
                "concept": "AdditionalPaidInCapitalCommonStock",
                "unit": "usd",
                "value": -61450
            },
            {
                "label": "",
                "concept": "RetainedEarningsAccumulatedDeficit",
                "unit": "usd",
                "value": -1191278
            },
            {
                "label": "",
                "concept": "StockholdersEquityIncludingPortionAttributableToNoncontrollingInterest",
                "unit": "usd",
                "value": -1132778
            },
            {
                "label": "",
                "concept": "LiabilitiesAndStockholdersEquity",
                "unit": "usd",
                "value": 8161
            }
        ],
        "cf": [
            {
                "label": "",
                "concept": "NetIncomeLoss",
                "unit": "usd",
                "value": -53833
            },
            {
                "label": "",
                "concept": "IncreaseDecreaseInPrepaidExpense",
                "unit": "usd",
                "value": -3000
            },
            {
                "label": "",
                "concept": "IncreaseDecreaseInAccountsPayable",
                "unit": "usd",
                "value": -2376
            },
            {
                "label": "",
                "concept": "IncreaseDecreaseInDeferredRevenue",
                "unit": "usd",
                "value": "N/A"
            },
            {
                "label": "",
                "concept": "IncreaseDecreaseInAccruedLiabilities",
                "unit": "usd",
                "value": 36000
            },
            {
                "label": "",
                "concept": "NetCashProvidedByUsedInOperatingActivities",
                "unit": "usd",
                "value": -17209
            },
            {
                "label": "",
                "concept": "NetCashProvidedByUsedInInvestingActivities",
                "unit": "usd",
                "value": "N/A"
            },
            {
                "label": "",
                "concept": "ProceedsFromRelatedPartyDebt",
                "unit": "usd",
                "value": 17877
            },
            {
                "label": "",
                "concept": "NetCashProvidedByUsedInFinancingActivities",
                "unit": "usd",
                "value": 17877
            },
            {
                "label": "",
                "concept": "CashCashEquivalentsRestrictedCashAndRestrictedCashEquivalentsPeriodIncreaseDecreaseExcludingExchangeRateEffect",
                "unit": "usd",
                "value": 668
            }
        ],
        "ic": [
            {
                "label": "",
                "concept": "Revenues",
                "unit": "usd",
                "value": "N/A"
            },
            {
                "label": "",
                "concept": "GeneralAndAdministrativeExpense",
                "unit": "usd",
                "value": 53833
            },
            {
                "label": "",
                "concept": "OperatingExpenses",
                "unit": "usd",
                "value": 53833
            },
            {
                "label": "",
                "concept": "OperatingIncomeLoss",
                "unit": "usd",
                "value": -53833
            },
            {
                "label": "",
                "concept": "IncomeLossFromContinuingOperationsBeforeIncomeTaxesExtraordinaryItemsNoncontrollingInterest",
                "unit": "usd",
                "value": -53833
            },
            {
                "label": "",
                "concept": "IncomeTaxExpenseBenefit",
                "unit": "usd",
                "value": "N/A"
            },
            {
                "label": "",
                "concept": "NetIncomeLoss",
                "unit": "usd",
                "value": -53833
            },
            {
                "label": "",
                "concept": "EarningsPerShareBasic",
                "unit": "usd/shares",
                "value": -0.0
            },
            {
                "label": "",
                "concept": "WeightedAverageNumberOfSharesOutstandingBasic",
                "unit": "shares",
                "value": 119950000
            }
        ]
    }
}