{
    "startDate": "2021-01-01",
    "endDate": "2021-03-31",
    "year": "2021",
    "quarter": "Q1",
    "symbol": "CELH",
    "data": {
        "bs": [
            {
                "label": "",
                "concept": "Cash",
                "unit": "usd",
                "value": 31634675
            },
            {
                "label": "",
                "concept": "AccountsReceivableNetCurrent",
                "unit": "usd",
                "value": 23997680
            },
            {
                "label": "",
                "concept": "NotesAndLoansReceivableNetCurrent",
                "unit": "usd",
                "value": 2509412
            },
            {
                "label": "",
                "concept": "InventoryNet",
                "unit": "usd",
                "value": 36891859
            },
            {
                "label": "",
                "concept": "PrepaidExpenseAndOtherAssetsCurrent",
                "unit": "usd",
                "value": 17183929
            },
            {
                "label": "",
                "concept": "AssetsCurrent",
                "unit": "usd",
                "value": 112217555
            },
            {
                "label": "",
                "concept": "NotesAndLoansReceivableNetNoncurrent",
                "unit": "usd",
                "value": 6900882
            },
            {
                "label": "",
                "concept": "PropertyPlantAndEquipmentNet",
                "unit": "usd",
                "value": 1169022
            },
            {
                "label": "",
                "concept": "OperatingLeaseRightOfUseAsset",
                "unit": "usd",
                "value": 791969
            },
            {
                "label": "",
                "concept": "FinanceLeaseRightOfUseAsset",
                "unit": "usd",
                "value": 129625
            },
            {
                "label": "",
                "concept": "DepositsAssets",
                "unit": "usd",
                "value": 110100
            },
            {
                "label": "",
                "concept": "IntangibleAssetsNetExcludingGoodwill",
                "unit": "usd",
                "value": 16439197
            },
            {
                "label": "",
                "concept": "Goodwill",
                "unit": "usd",
                "value": 10419321
            },
            {
                "label": "",
                "concept": "Assets",
                "unit": "usd",
                "value": 148177671
            },
            {
                "label": "",
                "concept": "AccountsPayableAndAccruedLiabilitiesCurrent",
                "unit": "usd",
                "value": 37525390
            },
            {
                "label": "",
                "concept": "OperatingLeaseLiabilityCurrent",
                "unit": "usd",
                "value": 337626
            },
            {
                "label": "",
                "concept": "FinanceLeaseLiabilityCurrent",
                "unit": "usd",
                "value": 192649
            },
            {
                "label": "",
                "concept": "OtherLiabilitiesCurrent",
                "unit": "usd",
                "value": 586954
            },
            {
                "label": "",
                "concept": "LiabilitiesCurrent",
                "unit": "usd",
                "value": 38642619
            },
            {
                "label": "",
                "concept": "OperatingLeaseLiabilityNoncurrent",
                "unit": "usd",
                "value": 436631
            },
            {
                "label": "",
                "concept": "FinanceLeaseLiabilityNoncurrent",
                "unit": "usd",
                "value": 87152
            },
            {
                "label": "",
                "concept": "Liabilities",
                "unit": "usd",
                "value": 39166402
            },
            {
                "label": "",
                "concept": "CommonStockValue",
                "unit": "usd",
                "value": 72586
            },
            {
                "label": "",
                "concept": "AdditionalPaidInCapital",
                "unit": "usd",
                "value": 164174742
            },
            {
                "label": "",
                "concept": "AccumulatedOtherComprehensiveIncomeLossNetOfTax",
                "unit": "usd",
                "value": -394651
            },
            {
                "label": "",
                "concept": "RetainedEarningsAccumulatedDeficit",
                "unit": "usd",
                "value": -54841408
            },
            {
                "label": "",
                "concept": "StockholdersEquity",
                "unit": "usd",
                "value": 109011269
            },
            {
                "label": "",
                "concept": "LiabilitiesAndStockholdersEquity",
                "unit": "usd",
                "value": 148177671
            }
        ],
        "cf": [
            {
                "label": "",
                "concept": "NetIncomeLoss",
                "unit": "usd",
                "value": 585424
            },
            {
                "label": "",
                "concept": "Depreciation",
                "unit": "usd",
                "value": 108198
            },
            {
                "label": "",
                "concept": "AdjustmentForAmortization",
                "unit": "usd",
                "value": 187670
            },
            {
                "label": "",
                "concept": "ProvisionForDoubtfulAccounts",
                "unit": "usd",
                "value": 223034
            },
            {
                "label": "",
                "concept": "celh:InventoryAllowanceForExcessAndObsoleteProducts",
                "unit": "usd",
                "value": -753935
            },
            {
                "label": "",
                "concept": "ShareBasedCompensation",
                "unit": "usd",
                "value": 3575001
            },
            {
                "label": "",
                "concept": "GainLossOnInvestments",
                "unit": "usd",
                "value": "N/A"
            },
            {
                "label": "",
                "concept": "IncreaseDecreaseInAccountsReceivable",
                "unit": "usd",
                "value": 9234501
            },
            {
                "label": "",
                "concept": "IncreaseDecreaseInInventories",
                "unit": "usd",
                "value": 19242172
            },
            {
                "label": "",
                "concept": "IncreaseDecreaseInPrepaidDeferredExpenseAndOtherAssets",
                "unit": "usd",
                "value": 2557007
            },
            {
                "label": "",
                "concept": "IncreaseDecreaseInAccountsPayableAndAccruedLiabilities",
                "unit": "usd",
                "value": 12112637
            },
            {
                "label": "",
                "concept": "celh:IncreaseDecreaseInDeferredRevenueAndOtherCurrentLiabilities",
                "unit": "usd",
                "value": 174355
            },
            {
                "label": "",
                "concept": "celh:ChangeInRightToUseAndLeaseObligationnet",
                "unit": "usd",
                "value": -4575
            },
            {
                "label": "",
                "concept": "NetCashProvidedByUsedInOperatingActivities",
                "unit": "usd",
                "value": -13318001
            },
            {
                "label": "",
                "concept": "ProceedsFromSaleOfNotesReceivable",
                "unit": "usd",
                "value": 1876273
            },
            {
                "label": "",
                "concept": "PaymentsToAcquirePropertyPlantAndEquipment",
                "unit": "usd",
                "value": 697843
            },
            {
                "label": "",
                "concept": "NetCashProvidedByUsedInInvestingActivities",
                "unit": "usd",
                "value": 1178430
            },
            {
                "label": "",
                "concept": "RepaymentsOfLongTermCapitalLeaseObligations",
                "unit": "usd",
                "value": 25149
            },
            {
                "label": "",
                "concept": "ProceedsFromStockOptionsExercised",
                "unit": "usd",
                "value": 715910
            },
            {
                "label": "",
                "concept": "NetCashProvidedByUsedInFinancingActivities",
                "unit": "usd",
                "value": 690761
            },
            {
                "label": "",
                "concept": "EffectOfExchangeRateOnCashAndCashEquivalents",
                "unit": "usd",
                "value": -164536
            },
            {
                "label": "",
                "concept": "CashCashEquivalentsRestrictedCashAndRestrictedCashEquivalentsPeriodIncreaseDecreaseIncludingExchangeRateEffect",
                "unit": "usd",
                "value": -11613346
            },
            {
                "label": "",
                "concept": "InterestPaidNet",
                "unit": "usd",
                "value": 1605
            }
        ],
        "ic": [
            {
                "label": "",
                "concept": "Revenues",
                "unit": "usd",
                "value": 50034879
            },
            {
                "label": "",
                "concept": "CostOfRevenue",
                "unit": "usd",
                "value": 29455784
            },
            {
                "label": "",
                "concept": "GrossProfit",
                "unit": "usd",
                "value": 20579095
            },
            {
                "label": "",
                "concept": "SellingAndMarketingExpense",
                "unit": "usd",
                "value": 11959053
            },
            {
                "label": "",
                "concept": "GeneralAndAdministrativeExpense",
                "unit": "usd",
                "value": 7806666
            },
            {
                "label": "",
                "concept": "OperatingExpenses",
                "unit": "usd",
                "value": 19765719
            },
            {
                "label": "",
                "concept": "OperatingIncomeLoss",
                "unit": "usd",
                "value": 813376
            },
            {
                "label": "",
                "concept": "InterestAndDividendIncomeOperating",
                "unit": "usd",
                "value": 86530
            },
            {
                "label": "",
                "concept": "InterestExpenseSubordinatedNotesAndDebentures",
                "unit": "usd",
                "value": "N/A"
            },
            {
                "label": "",
                "concept": "celh:InterestOnOtherObligations",
                "unit": "usd",
                "value": 1605
            },
            {
                "label": "",
                "concept": "celh:AmortizationOfDiscountOnBondsPayable",
                "unit": "usd",
                "value": "N/A"
            },
            {
                "label": "",
                "concept": "celh:OtherMiscellaneousExpense",
                "unit": "usd",
                "value": -11621
            },
            {
                "label": "",
                "concept": "GainLossOnTerminationOfLease",
                "unit": "usd",
                "value": "N/A"
            },
            {
                "label": "",
                "concept": "ForeignCurrencyTransactionGainLossBeforeTax",
                "unit": "usd",
                "value": -301256
            },
            {
                "label": "",
                "concept": "NonoperatingIncomeExpense",
                "unit": "usd",
                "value": -227952
            },
            {
                "label": "",
                "concept": "IncomeLossFromContinuingOperationsBeforeIncomeTaxesExtraordinaryItemsNoncontrollingInterest",
                "unit": "usd",
                "value": 585424
            },
            {
                "label": "",
                "concept": "IncomeTaxExpenseBenefit",
                "unit": "usd",
                "value": "N/A"
            },
            {
                "label": "",
                "concept": "NetIncomeLoss",
                "unit": "usd",
                "value": 585424
            },
            {
                "label": "",
                "concept": "OtherComprehensiveIncomeLossForeignCurrencyTransactionAndTranslationAdjustmentNetOfTax",
                "unit": "usd",
                "value": -192509
            },
            {
                "label": "",
                "concept": "ComprehensiveIncomeNetOfTax",
                "unit": "usd",
                "value": 392915
            },
            {
                "label": "",
                "concept": "EarningsPerShareBasic",
                "unit": "usd/shares",
                "value": 0.01
            },
            {
                "label": "",
                "concept": "EarningsPerShareDiluted",
                "unit": "usd/shares",
                "value": 0.01
            },
            {
                "label": "",
                "concept": "WeightedAverageNumberOfSharesOutstandingBasic",
                "unit": "shares",
                "value": 72516396
            },
            {
                "label": "",
                "concept": "WeightedAverageNumberOfDilutedSharesOutstanding",
                "unit": "shares",
                "value": 76925484
            }
        ]
    }
}