{
    "startDate": "2018-01-01",
    "endDate": "2018-03-31",
    "year": "2018",
    "quarter": "Q1",
    "symbol": "ELRA",
    "data": {
        "bs": [
            {
                "label": "",
                "concept": "Cash",
                "unit": "usd",
                "value": 22013
            },
            {
                "label": "",
                "concept": "AccountsReceivableRelatedPartiesCurrent",
                "unit": "usd",
                "value": 314619
            },
            {
                "label": "",
                "concept": "PrepaidExpenseCurrent",
                "unit": "usd",
                "value": 13988
            },
            {
                "label": "",
                "concept": "AssetsCurrent",
                "unit": "usd",
                "value": 350620
            },
            {
                "label": "",
                "concept": "PrepaidRent",
                "unit": "usd",
                "value": 26145
            },
            {
                "label": "",
                "concept": "Assets",
                "unit": "usd",
                "value": 376765
            },
            {
                "label": "",
                "concept": "AccountsPayableAndAccruedLiabilitiesCurrent",
                "unit": "usd",
                "value": 2286066
            },
            {
                "label": "",
                "concept": "AccountsPayableRelatedPartiesCurrent",
                "unit": "usd",
                "value": 2956439
            },
            {
                "label": "",
                "concept": "LoansPayableCurrent",
                "unit": "usd",
                "value": 59391
            },
            {
                "label": "",
                "concept": "OtherNotesPayableCurrent",
                "unit": "usd",
                "value": 44824
            },
            {
                "label": "",
                "concept": "SettlementLiabilitiesCurrent",
                "unit": "usd",
                "value": 2162159
            },
            {
                "label": "",
                "concept": "NotesAndLoansPayableCurrent",
                "unit": "usd",
                "value": 45429
            },
            {
                "label": "",
                "concept": "ConvertibleNotesPayableCurrent",
                "unit": "usd",
                "value": 3139492
            },
            {
                "label": "",
                "concept": "DerivativeLiabilities",
                "unit": "usd",
                "value": 390127
            },
            {
                "label": "",
                "concept": "Liabilities",
                "unit": "usd",
                "value": 11083927
            },
            {
                "label": "",
                "concept": "CommitmentsAndContingencies",
                "unit": "usd",
                "value": "N/A"
            },
            {
                "label": "",
                "concept": "CommonStockValue",
                "unit": "usd",
                "value": 2255390
            },
            {
                "label": "",
                "concept": "AdditionalPaidInCapital",
                "unit": "usd",
                "value": 15856664
            },
            {
                "label": "",
                "concept": "CommonStockShareSubscribedButUnissuedSubscriptionsReceivable",
                "unit": "usd",
                "value": 75672
            },
            {
                "label": "",
                "concept": "RetainedEarningsAccumulatedDeficit",
                "unit": "usd",
                "value": -28947649
            },
            {
                "label": "",
                "concept": "StockholdersEquity",
                "unit": "usd",
                "value": -10707162
            },
            {
                "label": "",
                "concept": "LiabilitiesAndStockholdersEquity",
                "unit": "usd",
                "value": 376765
            }
        ],
        "cf": [
            {
                "label": "",
                "concept": "NetIncomeLoss",
                "unit": "usd",
                "value": -329048
            },
            {
                "label": "",
                "concept": "AmortizationOfDebtDiscountPremium",
                "unit": "usd",
                "value": "N/A"
            },
            {
                "label": "",
                "concept": "GainLossOnDerivativeInstrumentsNetPretax",
                "unit": "usd",
                "value": 8
            },
            {
                "label": "",
                "concept": "IncreaseDecreaseInAccountsReceivableRelatedParties",
                "unit": "usd",
                "value": 104562
            },
            {
                "label": "",
                "concept": "IncreaseDecreaseInPrepaidExpense",
                "unit": "usd",
                "value": 18610
            },
            {
                "label": "",
                "concept": "IncreaseDecreaseInAccountsPayableAndAccruedLiabilities",
                "unit": "usd",
                "value": 168741
            },
            {
                "label": "",
                "concept": "IncreaseDecreaseInAccountsPayableRelatedParties",
                "unit": "usd",
                "value": 272430
            },
            {
                "label": "",
                "concept": "NetCashProvidedByUsedInOperatingActivities",
                "unit": "usd",
                "value": -11057
            },
            {
                "label": "",
                "concept": "ProceedsFromNotesPayable",
                "unit": "usd",
                "value": 10000
            },
            {
                "label": "",
                "concept": "RepaymentsOfShortTermDebt",
                "unit": "usd",
                "value": "N/A"
            },
            {
                "label": "",
                "concept": "NetCashProvidedByUsedInFinancingActivities",
                "unit": "usd",
                "value": 10000
            },
            {
                "label": "",
                "concept": "CashPeriodIncreaseDecrease",
                "unit": "usd",
                "value": -1057
            },
            {
                "label": "",
                "concept": "InterestPaid",
                "unit": "usd",
                "value": "N/A"
            },
            {
                "label": "",
                "concept": "IncomeTaxesPaid",
                "unit": "usd",
                "value": "N/A"
            },
            {
                "label": "",
                "concept": "StockIssuedDuringPeriodValueOther",
                "unit": "usd",
                "value": "N/A"
            }
        ],
        "ic": [
            {
                "label": "",
                "concept": "RevenueFromRelatedParties",
                "unit": "usd",
                "value": 149061
            },
            {
                "label": "",
                "concept": "GeneralAndAdministrativeExpense",
                "unit": "usd",
                "value": 295735
            },
            {
                "label": "",
                "concept": "OperatingExpenses",
                "unit": "usd",
                "value": 295735
            },
            {
                "label": "",
                "concept": "OperatingIncomeLoss",
                "unit": "usd",
                "value": -146674
            },
            {
                "label": "",
                "concept": "InterestExpense",
                "unit": "usd",
                "value": 182382
            },
            {
                "label": "",
                "concept": "GainLossOnDerivativeInstrumentsNetPretax",
                "unit": "usd",
                "value": 8
            },
            {
                "label": "",
                "concept": "OtherIncome",
                "unit": "usd",
                "value": -182374
            },
            {
                "label": "",
                "concept": "NetIncomeLoss",
                "unit": "usd",
                "value": -329048
            },
            {
                "label": "",
                "concept": "EarningsPerShareBasic",
                "unit": "usd/shares",
                "value": -0.0
            },
            {
                "label": "",
                "concept": "EarningsPerShareDiluted",
                "unit": "usd/shares",
                "value": 0.0
            },
            {
                "label": "",
                "concept": "WeightedAverageNumberOfSharesOutstandingBasic",
                "unit": "shares",
                "value": 2315835269
            },
            {
                "label": "",
                "concept": "ProFormaWeightedAverageSharesOutstandingDiluted",
                "unit": "shares",
                "value": 2315835269
            }
        ]
    }
}